linkmod/__init__.py
linkmod/linkmod.py
linkmod-1.0.1.dist-info/METADATA
linkmod-1.0.1.dist-info/WHEEL
linkmod-1.0.1.dist-info/entry_points.txt
linkmod-1.0.1.dist-info/top_level.txt
linkmod-1.0.1.dist-info/RECORD
