Metadata-Version: 2.4
Name: linkmod
Version: 1.0.1
Summary: A simple tool to customize links.
Home-page: https://github.com/Rishi-Bhati/linkmod.git
Author: Rishi Bhati
Author-email: bhatirishi5@gmail.com
Classifier: Programming Language :: Python :: 3
Classifier: License :: OSI Approved :: MIT License
Classifier: Operating System :: OS Independent
Requires-Python: >=3.6
Requires-Dist: requests
Requires-Dist: keyring
Dynamic: author
Dynamic: author-email
Dynamic: classifier
Dynamic: description
Dynamic: description-content-type
Dynamic: home-page
Dynamic: requires-dist
Dynamic: requires-python
Dynamic: summary
